Workbook

Sheet 总报价汇总
A1: Web3 Crypto Exchange - AWS安全架构与报价清单
A2: 区域: Middle East (me-south-1 / Bahrain) | 适用于迪拜VARA合规要求
A4: 关键假设 (Key Assumptions)
A5: 假设项 | B5: 数值 | C5: 说明
A6: UAT成本比例 - 基础设施 | B6: 0.35 | C6: 安全服务保持100%，基础设施约30-40%
A7: UAT成本比例 - 安全服务 | B7: 1 | C7: 渗透测试要求安全配置完全一致
A8: Production环境数量 | B8: 2 | C8: 客户需求: 2套Prod
A9: UAT环境数量 | B9: 1 | C9: 客户需求: 1套UAT
A10: 年度费用月数 | B10: 12
A11: Reserved Instance折扣率 | B11: 0.37 | C11: 1年期RI约37-41%折扣
A13: 报价汇总 (Monthly Cost Summary)
A14: 类别 | B14: 单环境月费(USD) | C14: Prod×2月费(USD) | D14: UAT×1月费(USD) | E14: 总月费(USD) | F14: 总年费(USD) | G14: 备注 | I14: 类别 | J14: 单环境月费 | K14: 2Prod+1UAT月费
A15: 安全服务 (Security Services) | B15: 7946 | C15: =B15*B8 | D15: =B15*B7*B9 | E15: =C15+D15 | F15: =E15*B10 | G15: 安全服务UAT需100%配置 | I15: 安全服务 | J15: 7946 | K15: =J15*2+J15*1
A16: 基础设施 (Infrastructure) | B16: 5132 | C16: =B16*B8 | D16: =B16*B6*B9 | E16: =C16+D16 | F16: =E16*B10 | G16: 基础设施UAT可缩减至35% | I16: 基础设施 | J16: 5132 | K16: =J16*2+J16*0.35
A17: 合计 (Total) | B17: =B15+B16 | C17: =C15+C16 | D17: =D15+D16 | E17: =E15+E16 | F17: =F15+F16 | G17: 2 Prod + 1 UAT ≈ 2.35x单环境
A19: 优化方案 (Reserved Instance + Savings Plans)
A20: 基础设施优化后月费(单环境) | B20: =B16*(1-B11) | C20: 应用1年期RI折扣后
A21: 优化后总月费(单环境) | B21: =B15+B20
A22: 优化后总月费(2Prod+1UAT) | B22: =(B15*B8+B15*B7*B9)+(B20*B8+B20*B6*B9)
A23: 优化后总年费(2Prod+1UAT) | B23: =B22*B10
A25: 重要说明:
A26: 1. 以上报价基于Dubai/ME区域(me-south-1)公开定价，实际费用可能因用量波动
A27: 2. Shield Advanced $3,000/月为全局费用(per payer account)，不需要每个环境单独付费
A28: 3. UAT环境安全服务必须与Production完全一致，以确保渗透测试结果有效
A29: 4. 2套Prod + 1套UAT总费用约为单环境的2.35倍(非简单翻倍)
A30: 5. 建议使用Reserved Instance(1年期)可节省37-41%基础设施费用
A31: 6. CloudHSM建议至少2台实现高可用(跨AZ部署)
A32: 7. 渗透测试费用另计，详见"渗透测试报价"工作表
D52: 关键洞察: 安全服务占总费用约60%，且UAT环境必须保持100%安全配置以满足渗透测试有效性要求。基础设施在UAT中可缩减至35%。

Sheet 安全服务报价
A1: AWS安全服务报价明细 - Middle East Region (me-south-1)
A3: 服务名称 | B3: 计费单位 | C3: 单价(USD) | D3: 预估用量 | E3: 月费估算(USD) | F3: 必要性 | G3: 说明
A4: AWS Shield Advanced | B4: 月订阅/组织 | C4: 3000 | D4: 1 | E4: =C4*D4 | F4: 必须 | G4: DDoS防护，含WAF费用，全局唯一费用
A5: AWS WAF | B5: Web ACL+规则+请求 | C5: 5 | D5: 1 | E5: 30 | F5: 必须 | G5: 1 ACL + 19规则 + 10M请求/月; $5+$19+$6
A6: Amazon GuardDuty | B6: 百万事件 | C6: 4 | D6: 1 | E6: 350 | F6: 必须 | G6: CT事件+VPC Flow+EKS审计+Runtime监控
A7: AWS Network Firewall | B7: 端点/小时 | C7: 0.395 | D7: 2 | E7: =C7*D7*720 | F7: 必须 | G7: 2个端点(Multi-AZ) + $0.065/GB处理费
A8: AWS CloudHSM | B8: HSM实例/小时 | C8: 1.88 | D8: 2 | E8: =C8*D8*720 | F8: 强烈推荐 | G8: 2台HSM实现HA(跨AZ); ME区域约$1.88/hr
A9: AWS KMS | B9: 密钥/月 | C9: 1 | D9: 10 | E9: =C9*D9+3 | F9: 必须 | G9: 10个CMK + API调用费约$3/月
A10: AWS Secrets Manager | B10: 密钥/月 | C10: 0.4 | D10: 15 | E10: =C10*D10 | F10: 必须 | G10: 15个密钥 + API调用费
A11: Amazon Inspector | B11: 实例/月 | C11: 1.258 | D11: 10 | E11: =C11*D11 | F11: 推荐 | G11: 10个EC2实例持续扫描
A12: AWS Security Hub | B12: 资源单位/月 | C12: 0.01 | D12: 50 | E12: =C12*D12 | F12: 必须 | G12: Essentials Plan; 聚合安全发现
A13: AWS Config | B13: 配置项 | C13: 0.003 | D13: 10000 | E13: =C13*D13+50 | F13: 必须 | G13: 10K配置项 + 50K规则评估($50)
A14: AWS CloudTrail | B14: 数据事件/100K | C14: 0.1 | D14: 500 | E14: =C14*D14 | F14: 必须 | G14: 管理事件免费; 数据事件按量
A15: Amazon CloudWatch | B15: 自定义指标+日志 | C15: 0.3 | D15: 50 | E15: =C15*D15+30 | F15: 必须 | G15: 50个自定义指标 + 日志存储$30
A16: AWS Audit Manager | B16: 评估/月 | C16: 0 | D16: 1 | E16: 0 | F16: 推荐 | G16: PCI DSS v4框架; 按评估收费
A17: AWS Firewall Manager | B17: 策略/区域 | C17: 100 | D17: 1 | E17: 100 | F17: 推荐 | G17: 集中管理WAF/SG/NF策略
A18: 安全服务月费合计 | E18: =SUM(E4:E17)
A19: 安全服务年费合计 | E19: =E18*12
A44: 关键洞察: Shield Advanced($3,000/月)和CloudHSM($2,708/月)占安全服务总费用的72%以上。Shield Advanced为全局费用(per payer account)，多环境不重复计费。

Sheet 基础设施报价
A1: AWS基础设施报价明细 - Middle East Region (me-south-1)
A2: 高可用Crypto Exchange工作负载配置
A4: 服务 | B4: 实例/配置 | C4: 单价(USD/hr) | D4: 数量 | E4: 月费估算(USD) | F4: 用途 | G4: 优化建议
A5: EKS Cluster | B5: 标准支持 | C5: 0.1 | D5: 2 | E5: =C5*D5*720 | F5: 容器编排(Prod+Staging) | G5: Extended Support: $0.60/hr
A6: EC2 Worker Nodes | B6: m5.xlarge (4vCPU/16GB) | C6: 0.235 | D6: 6 | E6: =C6*D6*720 | F6: EKS工作节点 | G6: 1年RI可节省37-41%
A7: EC2 Worker Nodes | B7: m5.2xlarge (8vCPU/32GB) | C7: 0.471 | D7: 3 | E7: =C7*D7*720 | F7: 重负载工作节点 | G7: Graviton可节省30%
A8: Aurora PostgreSQL | B8: db.r5.2xlarge Multi-AZ | C8: 0.68 | D8: 1 | E8: =C8*D8*720 | F8: 交易数据库 | G8: Multi-AZ自动故障转移
A9: Aurora Storage | B9: 500GB + I/O | C9: 0.1 | D9: 500 | E9: =C9*D9 | F9: 数据库存储 | G9: 按实际使用量计费
A10: ElastiCache Redis | B10: cache.m5.xlarge 集群模式 | C10: 0.34 | D10: 3 | E10: =C10*D10*720 | F10: 会话管理/缓存/订单簿 | G10: 1主+2副本
A11: ALB | B11: 2个ALB (API+Web) | C11: 0.03 | D11: 2 | E11: =C11*D11*720+50 | F11: HTTP/HTTPS负载均衡 | G11: +LCU费用约$50
A12: NLB | B12: 1个NLB (WebSocket/FIX) | C12: 0.03 | D12: 1 | E12: =C12*D12*720+20 | F12: TCP/WebSocket连接 | G12: +NLCU费用约$20
A13: CloudFront | B13: 5TB/月 ME分发 | C13: 0.11 | D13: 4000 | E13: =C13*D13 | F13: CDN全球加速 | G13: 首1TB免费
A14: S3 Storage | B14: 1TB Standard | C14: 0.027 | D14: 1000 | E14: =C14*D14 | F14: 对象存储/日志/备份 | G14: + 请求费用
A15: NAT Gateway | B15: 2个NAT GW + 500GB | C15: 0.055 | D15: 2 | E15: =C15*D15*720+500*0.055 | F15: 私有子网出站 | G15: 与NF链式部署可免费
A16: Data Transfer OUT | B16: 2TB/月 to Internet | C16: 0.11 | D16: 2000 | E16: =C16*D16 | F16: 出站数据传输 | G16: 入站免费
A17: 基础设施月费合计 | E17: =SUM(E5:E16)
A19: 高可用生产环境估算
A20: 基础配置月费 | E20: =E17
A21: 完整HA生产环境(含冗余) | E21: =E17*2.5 | G21: 含更多副本、更大实例、额外冗余

Sheet 环境配置对比
A1: Production vs UAT 环境配置对比
A2: 渗透测试有效性要求: 安全服务必须100%一致; 基础设施可缩减
A4: 服务类别 | B4: Production配置 | C4: UAT配置 | D4: 成本比例 | E4: 说明
A5: Compute (EC2) | B5: z1d/c6i.8xlarge, Multi-AZ, Auto Scaling (min 6节点) | C5: c6i.2xlarge或Graviton, Single-AZ, min 2节点, 非工作时间关闭 | D5: 20-30% | E5: 架构拓扑一致，规模缩减
A6: Database (Aurora/RDS) | B6: Multi-AZ, r6g.4xlarge, 读副本, Provisioned IOPS | C6: Single-AZ, r6g.xlarge, 无读副本, GP3存储 | D6: 25-35% | E6: 数据结构一致
A7: Matching Engine | B7: EC2 Cluster Placement Group, z1d.3xlarge, NVMe | C7: Cluster Placement Group(同拓扑), c6i.xlarge | D7: 30-40% | E7: 拓扑一致，实例缩小
A8: Load Balancing (ALB/NLB) | B8: Multi-AZ, 高吞吐 | C8: Single-AZ, 低容量 | D8: 40-50%
A9: AWS WAF | B9: 完整规则集(OWASP, Bot Control, Rate Limiting) | C9: 完整规则集 - 与Production完全一致 | D9: 100% | E9: 渗透测试必须
A10: GuardDuty | B10: 所有保护计划启用 | C10: 所有保护计划启用 | D10: 100% | E10: 渗透测试必须
A11: Security Hub | B11: 完整合规标准 | C11: 完整合规标准 | D11: 100% | E11: 渗透测试必须
A12: Shield Advanced | B12: 所有端点启用 | C12: 所有端点启用 | D12: 100% | E12: 全局费用，不额外收费
A13: KMS/Encryption | B13: CMKs, 信封加密 | C13: 完全一致的加密配置 | D13: 100% | E13: 渗透测试必须
A14: Network (VPC/SGs/NACLs) | B14: Multi-AZ, Transit Gateway, 完整分段 | C14: 同拓扑, Single-AZ, 相同安全组 | D14: 50-60% | E14: 网络隔离必须一致
A15: Monitoring (CloudWatch) | B15: 详细监控, 自定义指标, 告警 | C15: 基础监控, 减少保留期 | D15: 30-40%
A16: Storage (S3/EBS) | B16: gp3 Provisioned IOPS, 跨区域复制 | C16: gp3标准, 无复制 | D16: 20-30%
A17: Message Queue (MSK/SQS) | B17: Multi-AZ Kafka集群, 高吞吐 | C17: 单Broker, 减少分区 | D17: 25-35%
A18: CI/CD & Testing | B18: N/A (独立Pipeline) | C18: Spot实例用于负载测试 | D18: 15-25%
A19: 整体估算 | B19: 100% (基准) | C19: 约30-40% of Production | D19: 30-40% | E19: 综合比例
A22: 多环境成本计算
A23: 单Production环境月费 | B23: ='总报价汇总'!B17
A24: 2×Production月费 | B24: ='总报价汇总'!C17
A25: 1×UAT月费 | B25: ='总报价汇总'!D17
A26: 总月费 (2Prod + 1UAT) | B26: ='总报价汇总'!E17
A27: 倍数 (vs 单环境) | B27: ='总报价汇总'!E17/'总报价汇总'!B17

Sheet 架构总览
A1: AWS Crypto Exchange 安全架构分层
A2: 多层防御架构 - 满足OWASP + VARA合规要求
A4: 安全层 | B4: AWS服务 | C4: 用途 | D4: 配置要点 | E4: 对应OWASP
A5: Edge/Perimeter | B5: Amazon CloudFront | C5: 全球CDN, 边缘DDoS吸收 | D5: Origin Access Control, TLS 1.3, 制裁地区地理限制 | E5: A10 SSRF
A6: Edge/Perimeter | B6: Amazon Route 53 | C6: DNS + 健康检查 | D6: DNSSEC, 故障转移路由, Shield Advanced集成 | E6: -
A7: Edge/Perimeter | B7: AWS Shield Advanced | C7: DDoS防护 (L3/L4/L7) | D7: 始终在线检测, SRT支持, 自动L7缓解, 成本保护 | E7: SC10 DoS
A8: Edge/Perimeter | B8: AWS WAF | C8: Web应用防火墙 | D8: OWASP Top 10规则, 速率限制, Bot Control, IP信誉 | E8: A03 Injection
A9: Network | B9: AWS Network Firewall | C9: 有状态防火墙 + IDS/IPS | D9: Suricata规则, 域名过滤, TLS检查 | E9: A05 Misconfig
A10: Network | B10: VPC + Subnets | C10: 网络隔离 | D10: 多层: public(ALB), private-app(计算), private-data(DB) | E10: A01 Access
A11: Network | B11: Security Groups | C11: 实例级防火墙 | D11: 最小权限允许规则, SG间引用通信 | E11: A01 Access
A12: Network | B12: Network ACLs | C12: 子网级显式拒绝 | D12: 阻止已知恶意IP, 限制未使用端口 | E12: A05 Misconfig
A13: Network | B13: AWS Transit Gateway | C13: 中心网络枢纽 | D13: 连接VPC/VPN/Direct Connect; 隔离prod/UAT | E13: -
A14: Network | B14: AWS PrivateLink | C14: 私有API连接 | D14: Nitro Enclaves安全访问KMS/Secrets Manager | E14: A02 Crypto
A15: Compute | B15: AWS Nitro Enclaves | C15: 隔离密钥操作 | D15: 无持久存储, 无交互访问, 无外部网络; 密码学证明 | E15: A02 Crypto
... A27: Compliance | B27: AWS Firewall Manager | C27: 集中策略 | D27: 管理WAF/SG/NF规则跨多账户组织 | E27: A05 Misconfig

Sheet OWASP映射
A1: OWASP安全标准映射 - Web3 Crypto Exchange
A3: OWASP Web Application Top 10 (2021)
A4: OWASP类别 | B4: 风险描述(交易所场景) | C4: 所需安全控制 | D4: AWS服务映射 | E4: 优先级
A5: A01 - Broken Access Control | B5: 未授权访问钱包/交易账户/管理面板/提现功能 | C5: RBAC, deny-by-default, 钱包权限隔离, 多签提现 | D5: IAM, Cognito, WAF, Verified Permissions | E5: P0
A6: A02 - Cryptographic Failures | B6: 私钥泄露, 钱包种子短语暴露, API密钥弱加密 | C6: HSM密钥管理, 信封加密, TLS 1.3, 安全密钥仪式 | D6: KMS, CloudHSM, Nitro Enclaves, ACM | E6: P0
A7: A03 - Injection | B7: 交易查询SQL注入, 订单簿NoSQL注入, 区块链节点命令注入 | C7: 参数化查询, 输入清理, WAF SQLi/XSS规则 | D7: WAF (AMR规则), RDS, API Gateway验证 | E7: P0
A8: A04 - Insecure Design | B8: 交易引擎缺乏威胁建模, 提现无速率限制, 无熔断器 | C8: 威胁建模, 安全设计模式, 交易熔断器, 提现速度限制 | D8: Well-Architected, EventBridge, Step Functions | E8: P1
A9: A05 - Security Misconfiguration | B9: 暴露的区块链节点RPC端点, 默认凭证, 过宽CORS | C9: 加固配置, 自动配置审计, 最小权限 | D9: Config, Security Hub, Inspector, SSM | E9: P1
A10: A06 - Vulnerable Components | B10: 过时区块链节点软件, 未修补交易库, 脆弱智能合约依赖 | C10: 软件组成分析, 自动修补, 容器镜像扫描 | D10: ECR扫描, Inspector, SSM Patch Manager | E10: P1
A11: A07 - Auth Failures | B11: 弱MFA, 活跃交易中会话劫持, 登录API凭证填充 | C11: 硬件MFA(FIDO2), 自适应认证, 会话绑定IP/设备 | D11: Cognito(MFA/自适应), WAF(Bot Control) | E11: P0
A12: A08 - Software Integrity | B12: 被入侵CI/CD部署恶意代码, 篡改智能合约升级 | C12: 代码签名, 不可变部署管道, 供应链验证 | D12: Signer, CodePipeline, ECR签名, CloudTrail | E12: P1
A13: A09 - Logging Failures | B13: 未检测到未授权提现, 遗漏可疑交易模式 | C13: 实时交易监控, 异常检测, 全面审计日志 | D13: CloudWatch, CloudTrail, GuardDuty, Security Hub | E13: P0
A14: A10 - SSRF | B14: SSRF攻击内部区块链节点RPC, 访问元数据服务窃取凭证 | C14: URL输入验证, 网络分段, IMDSv2强制 | D14: WAF(SSRF规则), VPC SG, IMDSv2, PrivateLink | E14: P1
A16: OWASP API Security Top 10 (2023)
A17: OWASP类别 | B17: 风险描述(交易所场景) | C17: 所需安全控制 | D17: AWS服务映射 | E17: 优先级
A18: API1 - Broken Object Level Auth | B18: 访问他人钱包/交易历史, 操纵订单ID | C18: 每对象授权检查, 用户-资源所有权验证 | D18: Cognito, Verified Permissions, API Gateway | E18: P0
A19: API2 - Broken Authentication | B19: 被盗API密钥执行未授权交易, JWT令牌泄露 | C19: OAuth 2.0/OIDC, 短期令牌, API密钥轮换, mTLS | D19: Cognito, IAM(SigV4), API Gateway, Secrets Manager | E19: P0
A20: API3 - Broken Property Level Auth | B20: 交易响应暴露内部撮合细节, 账户设置批量赋值 | C20: 响应过滤, 属性级访问控制, 读写字段分离 | D20: API Gateway(响应映射), AppSync(字段级授权) | E20: P1
A21: API4 - Unrestricted Resource | B21: API滥用抓取市场数据, 订单洪水攻击 | C21: 速率限制, 节流, 请求配额, 基于成本的资源分配 | D21: API Gateway(节流/配额), WAF(速率规则), CloudFront | E21: P0
A22: API5 - Broken Function Level Auth | B22: 普通用户访问管理员提现审批API, 权限提升 | C22: 严格功能级RBAC, 独立管理API端点, 最小权限 | D22: IAM策略, Cognito组, Verified Permissions | E22: P0
A23: API6 - Unrestricted Sensitive Flows | B23: 自动化Bot利用做市API, 自动创建账户洗盘交易 | C23: Bot检测, CAPTCHA, 业务逻辑速率限制, 行为分析 | D23: WAF(Bot Control), Cognito(高级安全), Fraud Detector | E23: P1
A24: API7 - SSRF | B24: 通过Webhook URL的SSRF攻击内部区块链节点 | C24: URL验证, 外部端点白名单, 网络分段 | D24: WAF, VPC端点, PrivateLink, SG, IMDSv2 | E24: P1
A25: API8 - Security Misconfiguration | B25: 暴露API文档泄露交易引擎细节, 宽松CORS | C25: API网关加固, CORS限制, 错误消息清理 | D25: API Gateway(阶段设置), Config规则, Security Hub | E25: P1
A26: API9 - Improper Inventory | B26: 影子/废弃交易API仍可访问, 旧版本已知漏洞 | C26: API清单管理, 版本弃用策略, API发现扫描 | D26: API Gateway(阶段管理), Config, Inspector | E26: P1
A27: API10 - Unsafe Consumption | B27: 信任未验证的外部价格源, 未验证的区块链RPC响应 | C27: 所有外部API响应输入验证, 熔断器, 数据完整性检查 | D27: Lambda(验证逻辑), EventBridge, Step Functions | E27: P1
A29: OWASP Smart Contract Top 10 (2025)
A30: OWASP类别 | B30: 风险描述(交易所场景) | C30: 所需安全控制 | D30: AWS服务映射 | E30: 优先级
A31: SC01 - Access Control | B31: 未授权管理员访问交易所智能合约, 未保护初始化函数 | C31: 合约RBAC, 多签治理, 函数可见性限制 | D31: Nitro Enclaves, KMS, Step Functions(多审批) | E31: P0
A32: SC02 - Price Oracle Manipulation | B32: 操纵价格源影响代币上市, DEX集成定价利用 | C32: 去中心化预言机聚合, TWAP定价, 多数据源验证 | D32: AMB Access, CloudWatch(异常检测), Lambda | E32: P0
A33: SC03 - Logic Errors | B33: 错误费用计算, 有缺陷的代币交换逻辑 | C33: 形式化验证, 全面单元/集成测试, 第三方审计 | D33: CodeBuild, CodeGuru, CloudFormation | E33: P1
A34: SC04 - Lack of Input Validation | B34: 操纵交易参数, 通过构造输入绕过提现限制 | C34: 严格输入边界检查, require语句, SafeMath | D34: Lambda(链下验证), API Gateway, WAF | E34: P1
A35: SC05 - Reentrancy Attacks | B35: 通过递归提现调用耗尽热钱包合约 | C35: Checks-Effects-Interactions模式, 重入锁 | D35: Nitro Enclaves(隔离签名), CloudWatch(异常检测) | E35: P0
A36: SC06 - Unchecked External Calls | B36: 未检测到失败的代币转账, 跨链桥交互静默失败 | C36: 返回值检查, try/catch模式, 交易收据验证 | D36: AMB(交易监控), Step Functions, CloudWatch | E36: P1
A37: SC07 - Flash Loan Attacks | B37: 闪电贷资助的市场操纵, 治理攻击 | C37: 闪电贷检测, 多区块确认, 时间加权计算 | D37: AMB(区块监控), Kinesis(实时流), Lambda | E37: P0
A38: SC08 - Integer Overflow | B38: 余额计算错误, 费用/奖励算术错误 | C38: SafeMath库, Solidity 0.8+内置溢出检查 | D38: CodeBuild(静态分析), CodeGuru | E38: P1
A39: SC09 - Insecure Randomness | B39: 可预测的抽奖结果, 可利用的订单匹配随机选择 | C39: Chainlink VRF, commit-reveal方案 | D39: CloudHSM(安全随机), KMS(熵源), Nitro Enclaves | E39: P1
A40: SC10 - Denial of Service | B40: Gas耗尽攻击, 阻止提现, 订单结算Griefing攻击 | C40: Gas高效模式, pull-over-push提现, 紧急暂停 | D40: Shield Advanced, CloudWatch, Lambda(熔断器) | E40: P0

Sheet 渗透测试报价
A1: 渗透测试服务报价 - Web3 Crypto Exchange
A2: 遵循OWASP WSTG / PTES / OSSTMM方法论 | 迪拜/中东区域报价
A4: 报价假设
A5: 中东区域溢价 | B5: 0.3 | C5: 迪拜/ME地区20-40%溢价
A6: 双环境附加比例 | B6: 0.5 | C6: 测试Prod+UAT额外40-60%
A8: 测试领域 | B8: 方法论 | C8: 工期(天) | D8: 费用范围-低(USD) | E8: 费用范围-高(USD) | F8: 交付物
A9: Web应用(交易平台) | B9: OWASP WSTG, PTES | C9: 10-15 | D9: 15000 | E9: 30000 | F9: 技术报告, CVSS评分, PoC漏洞利用, 修复指南
A10: API测试(REST/WebSocket/Trading) | B10: OWASP WSTG(API), PTES | C10: 8-12 | D10: 15000 | E10: 30000 | F10: API漏洞报告, 认证/授权绕过, 业务逻辑缺陷
A11: 移动应用(iOS + Android) | B11: OWASP MASVS/MSTG, PTES | C11: 8-12 | D11: 15000 | E11: 40000 | F11: 移动安全报告, 本地存储分析, 证书固定评估
A12: 基础设施/云(AWS) | B12: PTES, OSSTMM, NIST 800-115 | C12: 10-15 | D12: 20000 | E12: 50000 | F12: 网络拓扑发现, 云配置错误, 权限提升路径
A13: 智能合约审计(Solidity/EVM) | B13: OWASP SCSTG, 手动审查 | C13: 15-30 | D13: 25000 | E13: 100000 | F13: 正式审计报告, 严重性分类, 修复验证, 审计证书
A14: 复测/修复验证 | B14: OWASP WSTG | C14: 3-5 | D14: 5000 | E14: 15000 | F14: 修复验证报告, 关闭确认
A15: 单环境合计 (54-89天) | D15: =SUM(D9:D14) | E15: =SUM(E9:E14)
A16: 中东区域溢价后 (单环境) | D16: =D15*(1+B5) | E16: =E15*(1+B5)
A17: 双环境(Prod+UAT)总费用 | D17: =D16*(1+B6) | E17: =E16*(1+B6)
A19: 补充说明:
A20: 1. 智能合约审计: Solidity(EVM)最具竞争力; Rust(Solana)溢价25-40%; Cairo(StarkNet)溢价30-45%
A21: 2. 加急费用: 1周(vs 4周)加收20-40%
A22: 3. 复审/修复轮次: 通常需要至少1轮修复验证，每轮$5,000-$20,000
A23: 4. VARA要求: 年度渗透测试 + 季度漏洞评估 + 关键系统TLPT
A24: 5. 2024年中东数据泄露平均成本$8.75M，充分证明安全投资的必要性
A25: 6. AWS Marketplace提供符合OWASP/NIST/PTES方法论的渗透测试服务

Sheet VARA合规要求
A1: Dubai VARA 技术安全合规要求
A2: Virtual Asset Regulatory Authority - Technology and Information Rulebook (2023, Updated May 2025)
A4: 要求类别 | B4: 具体要求 | C4: 合规控制措施 | D4: AWS服务支持
A5: 渗透测试 | B5: 年度渗透测试由合格独立第三方执行 | C5: 认证外部审计师; 新系统上线前测试; 结果提交VARA | D5: Inspector, Security Hub, Marketplace
A6: 渗透测试 | B6: 季度漏洞评估 | C6: 季度扫描+正式修复跟踪 | D6: Inspector, Config Rules
A7: 渗透测试 | B7: 威胁导向渗透测试(TLPT)在生产系统 | C7: 外部认证测试者; 覆盖关键/重要功能; 摘要提交VARA | D7: Shield Advanced, WAF, GuardDuty
A8: 智能合约安全 | B8: 静态/动态代码分析; 部署前第三方审计 | C8: 独立审计; 形式化验证; 已部署合约定期重评估 | D8: CodeBuild, CodeGuru
A9: 密钥管理 | B9: HSM密钥生成+职责分离 | C9: 硬件安全模块; 密钥生成正式验证; 全面审计日志 | D9: CloudHSM, KMS, CloudTrail
A10: 密钥管理 | B10: 无单点故障; 备份密钥独立存放 | C10: 多位置密钥存储; 备份与主密钥/种子短语分离 | D10: CloudHSM(跨AZ), Secrets Manager
A11: 多重签名 | B11: 高价值操作M > N/2签名者 | C11: 签名权限地理分布; 多样化授权机制; 定期测试 | D11: Nitro Enclaves, Step Functions
A12: 访问控制 | B12: 所有关键系统访问多因素认证 | C12: 硬件认证; 生物识别; 时间限制; 持续会话验证 | D12: Cognito(MFA), IAM Identity Center
A13: 网络安全 | B13: 网络分段+开发工作站隔离 | C13: 禁止直接生产访问; 端点保护; 安全密钥管理 | D13: VPC, Network Firewall, SSM
A14: 网络安全策略 | B14: CISO年度审查; 许可时提交VARA | C14: 覆盖信息安全/访问控制/智能合约/事件响应/硬件标准 | D14: Security Hub, Config, Audit Manager
A15: 事件响应 | B15: 重大网络安全事件72小时内通知VARA | C15: 根因分析; 修复活动; 事件后全面轮换密钥; 安全基线重建 | D15: GuardDuty, CloudTrail, EventBridge
... A23: 客户认证 | B23: 强MFA; 基于风险的挑战 | C23: 禁止即时通讯验证高风险操作; 可疑登录检测 | D23: Cognito, WAF Bot Control

Sheet 案例参考
A1: 真实案例与参考架构
A2: AWS Case Studies, Blog Posts, GitHub Samples & Solution Library
A4: AWS客户案例
A5: 公司 | B5: 来源类型 | C5: 关键架构模式 | D5: 安全特性 | E5: 日期 | F5: 关键成果
A6: Coinbase International | B6: Case Study | C6: EC2 z1d + Cluster Placement Groups + Aurora | D6: Nitro Enclaves, 百慕大金融监管 | E6: 2023 | F6: 100K msg/sec, 超低延迟
A7: OSL (香港) | B7: Case Study | C7: 微服务 on EKS + ECR + CI/CD | D7: Nitro Enclaves + KMS, SFC持牌 | E7: 2026 | F7: 支持2/3香港现货加密ETF
A8: RedotPay | B8: Case Study | C8: Aurora + ALB + EC2 + K8s + CodePipeline | D8: 数据安全, 合规基础设施 | E8: 2026 | F8: 500万+用户, 1周部署
A9: Auros | B9: Case Study | C9: 链上交易执行 | D9: Nitro Enclaves密钥保护 | E9: 2024 | F9: 安全链上交易无延迟妥协
A10: Crypto.com | B10: Case Study | C10: Transit Gateway多区域 + Gen AI | D10: 数据驻留合规, VPC隔离 | E10: 2024 | F10: 1亿用户, 90个国家
A11: Pionex US | B11: Case Study | C11: Aurora + Zero-ETL集成 | D11: 自动化加密交易 | E11: 2024 | F11: 延迟降低98%
A12: Itaú Bank | B12: Case Study | C12: Nitro Enclaves数字资产框架 | D12: 治理策略, 合规协议 | E12: 2024 | F12: 安全加密货币托管
A13: One Trading | B13: Blog Post | C13: EC2 CPG共享, 领导者-跟随者复制 | D13: 单AZ隔离, 多AZ韧性 | E13: 2023 | F13: Sub-200μs往返延迟
A14: Derive | B14: Blog Post | C14: Graviton on EKS + Aurora, 混合CEX/DEX | D14: 链上结算透明度, OP Stack L2 | E14: 2025 | F14: 低延迟去中心化交易
A15: Jupiter DEX | B15: Case Study | C15: CloudFront CDN + Solana路由 | D15: 60%延迟降低 | E15: 2025 | F15: Solana最大DEX聚合器
A17: AWS Blog Posts & 参考架构
A18: 标题 | B18: 来源 | C18: 关键内容 | D18: 日期
A19: Migrate CEX to AWS (Part 1&2) | B19: AWS Web3 Blog | C19: 无状态微服务交易引擎, 订单簿, 市场数据分发 | D19: Nov 2025
A20: Optimize tick-to-trade latency | B20: AWS Web3 Blog | C20: EC2计算优化, 内核旁路, 混合部署 | D20: Jul 2025
A21: Low latency cloud-native exchanges | B21: AWS Industries Blog | C21: EC2 CPG, ZeroMQ, Redis Streams, Kinesis, TGW Multicast | D21: Nov 2023
A23: aws-samples GitHub Repositories
A24: 仓库名称 | B24: 架构模式 | C24: 安全特性
A25: nitro-enclave-blockchain-wallet-on-eks | B25: EKS + Nitro Enclaves, Ethereum签名, CDK | C25: 隔离enclave密钥管理
A26: aws-nitro-enclave-blockchain-wallet | B26: Nitro Enclave钱包签名 | C26: 安全密钥隔离
A27: aws-blockchain-node-runners | B27: 云端区块链节点部署 | C27: 基础设施自动化
A28: digital-asset-portfolio-tracker | B28: React + Managed Blockchain Query, CDK | C28: BTC/ETH投资组合跟踪
A29: Guidance-for-Authentication-with-Digital-Wallets | B29: Cognito + API Gateway Web3代理 | C29: 临时凭证, dApp认证
A32: 云厂商安全能力对比
A33: 能力 | B33: AWS | C33: Azure | D33: GCP
A34: 机密计算 | B34: Nitro Enclaves (隔离VM, 无持久存储) | C34: Confidential VMs (AMD SEV-SNP, Intel SGX) | D34: Confidential VMs (AMD SEV, Intel TDX), Confidential Space
A35: HSM服务 | B35: CloudHSM - FIPS 140-2 L3, 单租户 | C35: Key Vault Managed HSM - FIPS 140-2 L3 | D35: Cloud HSM - FIPS 140-2 L3 (单租户2026 GA)
A36: DDoS防护 | B36: Shield Standard(免费) + Advanced($3K/月) | C36: DDoS Network Protection + IP Protection | D36: Cloud Armor Standard(免费) + Enterprise
A37: WAF | B37: AWS WAF (自定义规则, 托管规则, Bot Control) | C37: Azure WAF on App GW/Front Door (OWASP CRS) | D37: Cloud Armor WAF (预配置规则, 自适应保护)
A38: 区块链密钥签名 | B38: Nitro Enclaves + KMS + Secrets Manager (专用指南) | C38: Managed HSM + Confidential Computing | D38: Confidential Space + MPC (Fireblocks集成)
A39: 交易所专用指南 | B39: 专用CEX迁移指南(3部分, 2025年11月) | C39: 通用区块链/金融科技架构 | D39: MPC数字资产参考架构
A40: 案例数量 | B40: 10+ (Coinbase, OSL, RedotPay等) | C40: 有限 (无公开交易所案例) | D40: 2-3 (Blockchain.com, Fireblocks)
